acid_vault/VaultGui.pyw
acid_vault/__init__.py
acid_vault/constants.py
acid_vault/legacy_load.py
acid_vault/ssh.py
acid_vault/steganography.py
acid_vault/vault.py
acid_vault/version.py
acid_vault/widgets.py
acid_vault/__pycache__/constants.cpython-38.pyc
acid_vault/__pycache__/legacy_load.cpython-38.pyc
acid_vault/__pycache__/ssh.cpython-38.pyc
acid_vault/__pycache__/steganography.cpython-38.pyc
acid_vault/__pycache__/vault.cpython-38.pyc
acid_vault/__pycache__/version.cpython-38.pyc
acid_vault/__pycache__/widgets.cpython-38.pyc
acid_vault/vault/__init__.py
acid_vault/vault/vault.py
acid_vault/vault/helpers/__init__.py
acid_vault/vault/helpers/constants.py
acid_vault/vault/helpers/legacy_load.py
acid_vault/vault/helpers/ssh.py
acid_vault/vault/helpers/steganography.py
acid_vault/vault/helpers/version.py
tests/__init__.py
tests/fixtures.py
tests/unit_steganography_test.py
tests/unit_vault_test.py
acid_vault-2.1.0.dist-info/LICENSE
acid_vault-2.1.0.dist-info/METADATA
acid_vault-2.1.0.dist-info/WHEEL
acid_vault-2.1.0.dist-info/top_level.txt
acid_vault-2.1.0.dist-info/RECORD
