Metadata-Version: 2.1
Name: acid-vault
Version: 2.1.0
Summary: Python Password Vault
Home-page: https://github.com/svavelsyra/PyVault
Author: Nils Nyman-Waara
Author-email: acid_vault@h2so4.se
License: UNKNOWN
Platform: UNKNOWN
Classifier: Programming Language :: Python :: 3
Classifier: License :: OSI Approved :: GNU Affero General Public License v3
Classifier: Operating System :: OS Independent
Requires-Python: >=3.6
Requires-Dist: cryptography (>=3.0)
Requires-Dist: paramiko (>=2.7)
Requires-Dist: pillow (>=7.0)
